code_metrics_tracker-0.1.20.dist-info/licenses/LICENSE
codeqa/__init__.py
codeqa/cli.py
codeqa/gitignore_parser.py
codeqa/metrics.py
codeqa/metrics_parsing.py
codeqa/pattern_translator.py
codeqa/snapshot_manager.py
codeqa/templates/CODE_METRICS.md.template
codeqa/templates/codeqa.json.template
codeqa/templates/github-workflow.yml.template
code_metrics_tracker-0.1.20.dist-info/METADATA
code_metrics_tracker-0.1.20.dist-info/WHEEL
code_metrics_tracker-0.1.20.dist-info/entry_points.txt
code_metrics_tracker-0.1.20.dist-info/top_level.txt
code_metrics_tracker-0.1.20.dist-info/RECORD
