Metadata-Version: 2.4
Name: code-metrics-tracker
Version: 0.1.20
Summary: Code quality metrics tracking tool that combines Ruff, Radon, and cloc to generate detailed trends over time
Home-page: https://github.com/AgileWorksZA/codeqa
Author: AgileWorks
Author-email: info@agileworks.co.za
Project-URL: Bug Tracker, https://github.com/AgileWorksZA/codeqa/issues
Project-URL: Documentation, https://github.com/AgileWorksZA/codeqa/blob/main/README.md
Project-URL: Source Code, https://github.com/AgileWorksZA/codeqa
Keywords: code quality metrics analysis static complexity maintainability linting ruff radon
Classifier: Development Status :: 4 - Beta
Classifier: Intended Audience :: Developers
Classifier: Topic :: Software Development :: Quality Assurance
Classifier: Programming Language :: Python :: 3
Classifier: Programming Language :: Python :: 3.7
Classifier: Programming Language :: Python :: 3.8
Classifier: Programming Language :: Python :: 3.9
Classifier: Programming Language :: Python :: 3.10
Classifier: Programming Language :: Python :: 3.11
Classifier: License :: OSI Approved :: MIT License
Requires-Python: >=3.7
License-File: LICENSE
Requires-Dist: setuptools>=42.0.0
Requires-Dist: ruff>=0.0.254
Requires-Dist: radon>=5.1.0
Dynamic: author
Dynamic: author-email
Dynamic: classifier
Dynamic: description
Dynamic: description-content-type
Dynamic: home-page
Dynamic: keywords
Dynamic: license-file
Dynamic: project-url
Dynamic: requires-dist
Dynamic: requires-python
Dynamic: summary
